cvat_data_flow/__init__.py
cvat_data_flow/main.py
cvat_data_flow/src/__init__.py
cvat_data_flow/src/config_parser.py
cvat_data_flow/src/cvat_api.py
cvat_data_flow/src/cvat_data_flow.py
cvat_data_flow/src/dataset_builder.py
cvat_data_flow/src/utils/__init__.py
cvat_data_flow/src/utils/coco_converter.py
cvat_data_flow/src/utils/config_parser.py
cvat_data_flow-0.1.0.dist-info/.DS_Store
cvat_data_flow-0.1.0.dist-info/LICENSE
cvat_data_flow-0.1.0.dist-info/METADATA
cvat_data_flow-0.1.0.dist-info/WHEEL
cvat_data_flow-0.1.0.dist-info/top_level.txt
cvat_data_flow-0.1.0.dist-info/RECORD
