Metadata-Version: 2.1
Name: cvat-data-flow
Version: 0.1.0
Summary: A utility for working with CVAT data flow
Home-page: https://github.com/ai-iaguzhinskii/cvat_data_flow
Author: Aleksei Iaguzhinskii
Classifier: Programming Language :: Python :: 3
Classifier: License :: OSI Approved :: MIT License
Requires-Python: >=3.8
License-File: LICENSE
Requires-Dist: Pillow >=6.2.0
Requires-Dist: requests >=2.20.1
Requires-Dist: datumaro ==0.1.9
Requires-Dist: cvat-sdk ==2.1.0.post1
Requires-Dist: PyYAML ~=6.0
Requires-Dist: tqdm
Requires-Dist: coloredlogs
